{
  "hosting": {
    "amplifyhosting": {
      "service": "amplifyhosting",
      "providerPlugin": "awscloudformation",
      "type": "manual"
    }
  },
  "auth": {
    "53ningen": {
      "service": "Cognito",
      "serviceType": "managed",
      "providerPlugin": "awscloudformation",
      "dependsOn": [],
      "frontendAuthConfig": {
        "socialProviders": [],
        "usernameAttributes": [],
        "signupAttributes": [],
        "passwordProtectionSettings": {
          "passwordPolicyCharacters": []
        },
        "mfaTypes": [],
        "verificationMechanisms": []
      }
    }
  },
  "analytics": {
    "53ningen": {
      "service": "Pinpoint",
      "providerPlugin": "awscloudformation"
    }
  }
}